{
  "routes": [
    {
      "method": "GET",
      "path": "/items",
      "handler": "item.find",
      "config": {
        "policies": []
      }
    },
    {
      "method": "GET",
      "path": "/items/count",
      "handler": "item.count",
      "config": {
        "policies": []
      }
    },
    {
      "method": "GET",
      "path": "/items/:id",
      "handler": "item.findOne",
      "config": {
        "policies": []
      }
    },
    {
      "method": "POST",
      "path": "/items",
      "handler": "item.create",
      "config": {
        "policies": []
      }
    },
    {
      "method": "PUT",
      "path": "/items/:id",
      "handler": "item.update",
      "config": {
        "policies": []
      }
    },
    {
      "method": "DELETE",
      "path": "/items/:id",
      "handler": "item.delete",
      "config": {
        "policies": []
      }
    }
  ]
}
